<?xml version="1.0"?>
<updates>
	<update>
		<name>Bootstrap Icons</name>
		<description>Bootstrap Icons for Joomla! Plugin Version 1.7.0</description>
		<element>bi</element>
		<type>plugin</type>
		<folder>system</folder>
		<version>1.7.0</version>
		<client>site</client>
		<infourl title="Bootstrap Icons">https://github.com/al-kln/joomla4-plg-bi/releases/tag/1.7.0</infourl>
		<downloads>
			<downloadurl type="full" format="zip">https://github.com/al-kln/joomla4-plg-bi/archive/refs/tags/1.7.0.zip</downloadurl>
		</downloads>
		<tags>
			<tag>stable</tag>
		</tags>
		<sha256>c5af39b65aff32822a810cb3331c8659214f88ab3809096c3e239e0aaf4e1677</sha256>
		<maintainer>Alexander Klein</maintainer>
		<maintainerurl>https://fact-werbeagentur.de</maintainerurl>
		<targetplatform name="joomla" version="(4\.0)" />
		<php_minimum>7.2</php_minimum>
	</update>
</updates>
